endoc/__init__.py
endoc/client.py
endoc/decorators.py
endoc/endoc_client.py
endoc/queries.py
endoc/models/document_search.py
endoc/models/note_library.py
endoc/models/paginated_search.py
endoc/models/single_paper.py
endoc/models/summarization.py
endoc/services/document_search.py
endoc/services/get_note_library.py
endoc/services/paginated_search.py
endoc/services/single_paper_search.py
endoc/services/summarization.py
endoc-1.7.0.dist-info/licenses/LICENSE
endoc-1.7.0.dist-info/METADATA
endoc-1.7.0.dist-info/WHEEL
endoc-1.7.0.dist-info/top_level.txt
endoc-1.7.0.dist-info/RECORD
