Metadata-Version: 2.4
Name: endoc
Version: 1.7.0
Summary: Endoc SDK: A note-taking app SDK powered by LLMs
Author-email: Grigor Dochev <gdochev@ethz.ch>, Andreas Giannoutsos <agiannoutsos@ethz.ch>
License: MIT
Project-URL: Homepage, https://github.com/science-editor/endoc-sdk
Classifier: Programming Language :: Python :: 3
Classifier: Programming Language :: Python :: 3.7
Classifier: Programming Language :: Python :: 3.8
Classifier: Programming Language :: Python :: 3.9
Classifier: Programming Language :: Python :: 3.10
Classifier: License :: OSI Approved :: MIT License
Classifier: Operating System :: OS Independent
Requires-Python: >=3.7
License-File: LICENSE
Requires-Dist: gql[requests]>=3.5.0
Dynamic: license-file
